{
  "project_info": {
    "project_number": "484990867375",
    "project_id": "barber-app-944c8",
    "storage_bucket": "barber-app-944c8.firebasestorage.app"
  },
  "client": [
    {
      "client_info": {
        "mobilesdk_app_id": "1:484990867375:android:c4dffaaf162e9a655ac15a",
        "android_client_info": {
          "package_name": "com.example.barber_app"
        }
      },
      "oauth_client": [],
      "api_key": [
        {
          "current_key": "AIzaSyDAmPhiVmXqEDMr4OSy6oUxzmGm2-qnVDs"
        }
      ],
      "services": {
        "appinvite_service": {
          "other_platform_oauth_client": []
        }
      }
    }
  ],
  "configuration_version": "1"
}